evolutionapi/__init__.py
evolutionapi/client.py
evolutionapi/exceptions.py
evolutionapi/models/__init__.py
evolutionapi/models/call.py
evolutionapi/models/chat.py
evolutionapi/models/group.py
evolutionapi/models/instance.py
evolutionapi/models/label.py
evolutionapi/models/message.py
evolutionapi/models/presence.py
evolutionapi/models/profile.py
evolutionapi/models/websocket.py
evolutionapi/services/__init__.py
evolutionapi/services/call.py
evolutionapi/services/chat.py
evolutionapi/services/group.py
evolutionapi/services/instance.py
evolutionapi/services/instance_operations.py
evolutionapi/services/label.py
evolutionapi/services/message.py
evolutionapi/services/profile.py
evolutionapi/services/websocket.py
evolution_sdk_python-0.0.1.dist-info/METADATA
evolution_sdk_python-0.0.1.dist-info/WHEEL
evolution_sdk_python-0.0.1.dist-info/RECORD
