Metadata-Version: 2.4
Name: evolution-sdk-python
Version: 0.0.1
Summary: Client Python para a API Evolution
Project-URL: Homepage, https://github.com/jacksonvieiracs/evolution-sdk-python
Project-URL: Repository, https://github.com/jacksonvieiracs/evolution-sdk-python
Project-URL: Issues, https://github.com/jacksonvieiracs/evolution-sdk-python
Author-email: Jackson Vieira <dev.jacksonvieira@gmail.com>, Davidson Gomes <contato@agenciadgcode.com>
License: MIT
Keywords: api,client,evolution,whatsapp
Classifier: Development Status :: 4 - Beta
Classifier: Intended Audience :: Developers
Classifier: Programming Language :: Python :: 3
Classifier: Programming Language :: Python :: 3.8
Classifier: Programming Language :: Python :: 3.9
Classifier: Programming Language :: Python :: 3.10
Classifier: Programming Language :: Python :: 3.11
Classifier: Programming Language :: Python :: 3.12
Requires-Python: >=3.8
Requires-Dist: python-socketio>=5.11.1
Requires-Dist: requests-toolbelt>=1.0.0
Requires-Dist: requests>=2.25.1
